src/__init__.py
src/fake.py
fhir_faker-0.0.8.dist-info/LICENSE
fhir_faker-0.0.8.dist-info/METADATA
fhir_faker-0.0.8.dist-info/WHEEL
fhir_faker-0.0.8.dist-info/top_level.txt
fhir_faker-0.0.8.dist-info/RECORD
