Metadata-Version: 2.1
Name: fhir-faker
Version: 0.0.8
Summary: A library for generating fake FHIR resources and data types.
Home-page: https://github.com/null-none/fhir-faker
Author: Kalinin Dmitry <kalinin.mitko@gmail.com>
License: MIT
Keywords: python,fhir,resources,faker
Platform: UNKNOWN
Classifier: Programming Language :: Python
Classifier: Programming Language :: Python :: 2.7
Classifier: Programming Language :: Python :: 3.4
Classifier: Programming Language :: Python :: 3.5
Classifier: Programming Language :: Python :: 3.6
License-File: LICENSE
Requires-Dist: Faker (==9.8.1)
